mult/__init__.py
mult/main.py
mult/master_test.py
mult/test.py
mult/outer_env_test/master.py
mult/outer_env_test/slave.py
mult/slave_test/slave_test.py
mult/src/master.py
mult/src/slave.py
mult-1.1.1.dist-info/METADATA
mult-1.1.1.dist-info/WHEEL
mult-1.1.1.dist-info/top_level.txt
mult-1.1.1.dist-info/RECORD
